sanatio/__init__.py
sanatio/code_generation/generate_code.cpython-39-x86_64-linux-gnu.so
sanatio/code_generation/__init__.py
sanatio/code_generation/raw_codes/metrics_codes.py
sanatio/code_generation/raw_codes/regression_search_codes.py
sanatio/code_generation/raw_codes/classification_search_codes.py
sanatio/code_generation/raw_codes/preprocessing_codes.py
sanatio/na_helper/fill_na.cpython-39-x86_64-linux-gnu.so
sanatio/na_helper/__init__.py
sanatio/na_helper/single_imputation.cpython-39-x86_64-linux-gnu.so
sanatio/validations/sanatio_enact.cpython-39-x86_64-linux-gnu.so
sanatio/validations/__init__.py
sanatio/validations/session_authentication.cpython-39-x86_64-linux-gnu.so
sanatio/validations/stats/__init__.py
sanatio/validations/stats/stats.cpython-39-x86_64-linux-gnu.so
sanatio/validations/stats/correlation_structure.cpython-39-x86_64-linux-gnu.so
sanatio/validations/routines/tree_based_classification_routine.cpython-39-x86_64-linux-gnu.so
sanatio/validations/routines/binary_logistic_regression_routine.cpython-39-x86_64-linux-gnu.so
sanatio/validations/routines/__init__.py
sanatio/validations/routines/helper_routines.cpython-39-x86_64-linux-gnu.so
sanatio/validations/routines/linear_regression_routine.cpython-39-x86_64-linux-gnu.so
sanatio/validations/graphs/graphs.cpython-39-x86_64-linux-gnu.so
sanatio/validations/graphs/__init__.py
sanatio/validation_tests/test_fill_na.cpython-39-x86_64-linux-gnu.so
sanatio/validation_tests/test_routines.cpython-39-x86_64-linux-gnu.so
sanatio/validation_tests/test_correlation_structure.cpython-39-x86_64-linux-gnu.so
sanatio/validation_tests/test_enact.cpython-39-x86_64-linux-gnu.so
sanatio/validation_tests/test_graphs.cpython-39-x86_64-linux-gnu.so
sanatio/validation_tests/test_code_generation.cpython-39-x86_64-linux-gnu.so
sanatio/validation_tests/__init__.py
sanatio/validation_tests/test_cf.cpython-39-x86_64-linux-gnu.so
sanatio/validation_tests/test_stats.cpython-39-x86_64-linux-gnu.so
fluidai_sanatio-2.2.3.dist-info/LICENSE
fluidai_sanatio-2.2.3.dist-info/WHEEL
fluidai_sanatio-2.2.3.dist-info/top_level.txt
fluidai_sanatio-2.2.3.dist-info/METADATA
fluidai_sanatio-2.2.3.dist-info/RECORD
