Metadata-Version: 2.1
Name: fluidai-sanatio
Version: 2.2.3
Summary: Run different validation tests on machine learning models.
Home-page: https://github.com/
Author: FluidAI
Author-email: info@fluid.ai
Classifier: Programming Language :: Python :: 3
Classifier: License :: OSI Approved :: GNU General Public License v3 or later (GPLv3+)
Classifier: Operating System :: OS Independent
Requires-Python: >=3.6
License-File: LICENSE
Requires-Dist: pandas
Requires-Dist: matplotlib
Requires-Dist: scikit-plot
Requires-Dist: sklearn
Requires-Dist: statsmodels
Requires-Dist: Pillow
Requires-Dist: tabulate
Requires-Dist: seaborn
Requires-Dist: xgboost
Requires-Dist: scipy
Requires-Dist: numpy
Requires-Dist: flask
Requires-Dist: sqlalchemy
Requires-Dist: markdown
Requires-Dist: mdutils
Requires-Dist: jupyter
Requires-Dist: ipython
Requires-Dist: pymssql
Requires-Dist: requests
Requires-Dist: coverage
Requires-Dist: coverage-badge
Requires-Dist: pytest
Requires-Dist: pytest-cov
Requires-Dist: auto-sklearn
Requires-Dist: cython
Requires-Dist: cornac
Requires-Dist: joblib
Requires-Dist: ipywidgets
Requires-Dist: airtable
Requires-Dist: datetime
